facerec21/__init__.py
facerec21-0.0.1.dist-info/LICENSE
facerec21-0.0.1.dist-info/METADATA
facerec21-0.0.1.dist-info/WHEEL
facerec21-0.0.1.dist-info/top_level.txt
facerec21-0.0.1.dist-info/RECORD
